{
  "requestsFinished": 1,
  "requestsFailed": 0,
  "requestsRetries": 0,
  "requestsFailedPerMinute": 0,
  "requestsFinishedPerMinute": 15,
  "requestMinDurationMillis": 1086,
  "requestMaxDurationMillis": 1086,
  "requestTotalFailedDurationMillis": 0,
  "requestTotalFinishedDurationMillis": 1086,
  "crawlerStartedAt": "2026-07-16T19:45:44.424Z",
  "crawlerFinishedAt": "2026-07-16T19:45:48.385Z",
  "statsPersistedAt": "2026-07-16T19:45:48.385Z",
  "crawlerRuntimeMillis": 4019,
  "crawlerLastStartTimestamp": 1784231144366,
  "requestRetryHistogram": [
    1
  ],
  "statsId": 2,
  "requestAvgFailedDurationMillis": null,
  "requestAvgFinishedDurationMillis": 1086,
  "requestTotalDurationMillis": 1086,
  "requestsTotal": 1,
  "requestsWithStatusCode": {},
  "errors": {},
  "retryErrors": {}
}